README.md
setup.py
./src/CMakeLists.txt
./src/bin
./src/include
./src/lib
./src/pybind11
./src/python
./src/bin/CMakeLists.txt
./src/bin/get_id.cpp
./src/bin/servo.cpp
./src/bin/set_id.cpp
./src/include/ics-servo
./src/include/ics-servo/ics.h
./src/include/ics-servo/ioprovider.h
./src/include/ics-servo/servo.h
./src/lib/CMakeLists.txt
./src/lib/ioprovider.cpp
./src/lib/servo.cpp
./src/pybind11/CMakeLists.txt
./src/pybind11/CONTRIBUTING.md
./src/pybind11/ISSUE_TEMPLATE.md
./src/pybind11/LICENSE
./src/pybind11/MANIFEST.in
./src/pybind11/README.md
./src/pybind11/docs
./src/pybind11/include
./src/pybind11/pybind11
./src/pybind11/setup.cfg
./src/pybind11/setup.py
./src/pybind11/tests
./src/pybind11/tools
./src/pybind11/docs/Doxyfile
./src/pybind11/docs/Makefile
./src/pybind11/docs/_static
./src/pybind11/docs/advanced
./src/pybind11/docs/basics.rst
./src/pybind11/docs/benchmark.py
./src/pybind11/docs/benchmark.rst
./src/pybind11/docs/changelog.rst
./src/pybind11/docs/classes.rst
./src/pybind11/docs/compiling.rst
./src/pybind11/docs/conf.py
./src/pybind11/docs/faq.rst
./src/pybind11/docs/index.rst
./src/pybind11/docs/intro.rst
./src/pybind11/docs/limitations.rst
./src/pybind11/docs/pybind11-logo.png
./src/pybind11/docs/pybind11_vs_boost_python1.png
./src/pybind11/docs/pybind11_vs_boost_python1.svg
./src/pybind11/docs/pybind11_vs_boost_python2.png
./src/pybind11/docs/pybind11_vs_boost_python2.svg
./src/pybind11/docs/reference.rst
./src/pybind11/docs/release.rst
./src/pybind11/docs/requirements.txt
./src/pybind11/docs/upgrade.rst
./src/pybind11/docs/_static/theme_overrides.css
./src/pybind11/docs/advanced/cast
./src/pybind11/docs/advanced/classes.rst
./src/pybind11/docs/advanced/embedding.rst
./src/pybind11/docs/advanced/exceptions.rst
./src/pybind11/docs/advanced/functions.rst
./src/pybind11/docs/advanced/misc.rst
./src/pybind11/docs/advanced/pycpp
./src/pybind11/docs/advanced/smart_ptrs.rst
./src/pybind11/docs/advanced/cast/chrono.rst
icsservo.egg-info/PKG-INFO
icsservo.egg-info/SOURCES.txt
icsservo.egg-info/dependency_links.txt
icsservo.egg-info/not-zip-safe
icsservo.egg-info/top_level.txt